[{"name":"minilog","description":null,"location":"minilog/index.html","searchKeys":["minilog"]},{"name":"nl.stanroelofs.minilog","description":null,"location":"minilog/nl.stanroelofs.minilog/index.html","searchKeys":["nl.stanroelofs.minilog"]},{"name":"ILoggerFactory","description":null,"location":"minilog/nl.stanroelofs.minilog/-i-logger-factory/index.html","searchKeys":["ILoggerFactory"]},{"name":"LoggerFactory","description":null,"location":"minilog/nl.stanroelofs.minilog/-logger-factory/index.html","searchKeys":["LoggerFactory"]},{"name":"Logging","description":null,"location":"minilog/nl.stanroelofs.minilog/-logging.html","searchKeys":["Logging"]},{"name":"nl.stanroelofs.minilog.logger","description":null,"location":"minilog/nl.stanroelofs.minilog.logger/index.html","searchKeys":["nl.stanroelofs.minilog.logger"]},{"name":"DefaultFormatter","description":null,"location":"minilog/nl.stanroelofs.minilog.logger/-default-formatter/index.html","searchKeys":["DefaultFormatter"]},{"name":"FileWriter","description":null,"location":"minilog/nl.stanroelofs.minilog.logger/-file-writer/index.html","searchKeys":["FileWriter"]},{"name":"Formatter","description":null,"location":"minilog/nl.stanroelofs.minilog.logger/-formatter/index.html","searchKeys":["Formatter"]},{"name":"Level","description":null,"location":"minilog/nl.stanroelofs.minilog.logger/-level/index.html","searchKeys":["Level"]},{"name":"DEBUG","description":null,"location":"minilog/nl.stanroelofs.minilog.logger/-level/-d-e-b-u-g/index.html","searchKeys":["DEBUG"]},{"name":"ERROR","description":null,"location":"minilog/nl.stanroelofs.minilog.logger/-level/-e-r-r-o-r/index.html","searchKeys":["ERROR"]},{"name":"INFO","description":null,"location":"minilog/nl.stanroelofs.minilog.logger/-level/-i-n-f-o/index.html","searchKeys":["INFO"]},{"name":"OFF","description":null,"location":"minilog/nl.stanroelofs.minilog.logger/-level/-o-f-f/index.html","searchKeys":["OFF"]},{"name":"WARNING","description":null,"location":"minilog/nl.stanroelofs.minilog.logger/-level/-w-a-r-n-i-n-g/index.html","searchKeys":["WARNING"]},{"name":"Logger","description":null,"location":"minilog/nl.stanroelofs.minilog.logger/-logger/index.html","searchKeys":["Logger"]},{"name":"LogMessage","description":null,"location":"minilog/nl.stanroelofs.minilog.logger/-log-message/index.html","searchKeys":["LogMessage"]},{"name":"SystemOutWriter","description":null,"location":"minilog/nl.stanroelofs.minilog.logger/-system-out-writer/index.html","searchKeys":["SystemOutWriter"]},{"name":"Writer","description":null,"location":"minilog/nl.stanroelofs.minilog.logger/-writer/index.html","searchKeys":["Writer"]}]
